LICENSE.txt
MANIFEST.in
README.md
requirements.txt
setup.py
supertree-commercial-license.pdf
supertree/__init__.py
supertree/model_loader.py
supertree/node.py
supertree/supertree.py
supertree/templatehtml.py
supertree/treedata.py
supertree.egg-info/PKG-INFO
supertree.egg-info/SOURCES.txt
supertree.egg-info/dependency_links.txt
supertree.egg-info/requires.txt
supertree.egg-info/top_level.txt
supertree/js/style.css
supertree/js/supertree.min.js